<?xml version="1.0"?>
<save_state>
	<window />
	<input />
	<textures />
	<audio>
		<music value="20" />
		<sfx value="20" />
	</audio>
	<pathfinder />
	<logoScene />
	<titleScene />
	<battle />
	<stages />
	<scene />
	<map />
	<EntityManager>
		<playerpos x="950" y="1730" />
		<actualStage stage="2" />
		<stats />
	</EntityManager>
	<pauseMenu />
	<conf />
	<inventory />
	<stmen />
	<shop />
	<guiManager />
	<fonts />
	<dialogSystem />
	<collisions />
	<fade />
	<camera>
		<camera x="-1299" y="-3100" />
	</camera>
	<renderer />
</save_state>
